vietnamadminunits/__init__.py
vietnamadminunits/converter/__init__.py
vietnamadminunits/converter/converter_2025.py
vietnamadminunits/database/__init__.py
vietnamadminunits/database/main.py
vietnamadminunits/pandas/__init__.py
vietnamadminunits/pandas/main.py
vietnamadminunits/parser/__init__.py
vietnamadminunits/parser/objects.py
vietnamadminunits/parser/parser_from_2025.py
vietnamadminunits/parser/parser_legacy.py
vietnamadminunits/parser/utils.py
vietnamadminunits_update-1.0.1.dist-info/licenses/LICENSE
vietnamadminunits_update-1.0.1.dist-info/METADATA
vietnamadminunits_update-1.0.1.dist-info/WHEEL
vietnamadminunits_update-1.0.1.dist-info/top_level.txt
vietnamadminunits_update-1.0.1.dist-info/RECORD
